csc_docker_pool/__init__.py
csc_docker_pool/args_util.py
csc_docker_pool/config_cli.py
csc_docker_pool/docker_util.py
csc_docker_pool/node.py
csc_docker_pool/relay_cli.py
csc_docker_pool/skeleton.py
csc_docker_pool/validator_cli.py
csc_docker_pool/wallet_cli.py
csc_docker_pool/assets/__init__.py
csc_docker_pool/assets/brand.txt
csc_docker_pool-0.1.dev40.dist-info/LICENSE.txt
csc_docker_pool-0.1.dev40.dist-info/METADATA
csc_docker_pool-0.1.dev40.dist-info/WHEEL
csc_docker_pool-0.1.dev40.dist-info/entry_points.txt
csc_docker_pool-0.1.dev40.dist-info/top_level.txt
csc_docker_pool-0.1.dev40.dist-info/RECORD
