Metadata-Version: 2.1
Name: csc-docker-pool
Version: 0.1.dev40
Summary: Add a short description here!
Home-page: https://github.com/pyscaffold/pyscaffold/
Author: maso
Author-email: mostafa.barmshory@gmail.com
License: MIT
Project-URL: Documentation, https://pyscaffold.org/
Project-URL: Source, https://github.com/genz-bank/csc-docker-pool
Platform: Linux
Classifier: Development Status :: 4 - Beta
Classifier: Programming Language :: Python
Requires-Python: >=3.9
License-File: LICENSE.txt
Requires-Dist: docker
Requires-Dist: pandas
Requires-Dist: importlib-metadata ; python_version < "3.8"
Provides-Extra: testing
Requires-Dist: setuptools ; extra == 'testing'
Requires-Dist: pytest ; extra == 'testing'
Requires-Dist: pytest-cov ; extra == 'testing'
